cheesemaker
