Metadata-Version: 1.1
Name: cheesemaker
Version: 0.3.8
Summary: A minimalistic image viewer using Python3 and PyQt5
Home-page: https://github.com/riverrun/cheesemaker
Author: David Whitlock
Author-email: alovedalongthe@gmail.com
License: GPLv3
Platform: UNKNOWN
Classifier: Development Status :: 4 - Beta
Classifier: Environment :: X11 Applications :: Qt
Classifier: Intended Audience :: End Users/Desktop
Classifier: Intended Audience :: Developers
Classifier: License :: OSI Approved :: GNU General Public License v3 (GPLv3)
Classifier: Operating System :: POSIX
Classifier: Programming Language :: Python
Classifier: Programming Language :: Python :: 3
Classifier: Topic :: Multimedia :: Graphics
Classifier: Topic :: Multimedia :: Graphics :: Viewers
